table_logger/__init__.py
table_logger/_version.py
table_logger/fmt.py
table_logger/table_logger.py
table_logger-0.3.6.dist-info/LICENSE
table_logger-0.3.6.dist-info/METADATA
table_logger-0.3.6.dist-info/WHEEL
table_logger-0.3.6.dist-info/top_level.txt
table_logger-0.3.6.dist-info/RECORD
