Metadata-Version: 1.1
Name: table-logger
Version: 0.3.6
Summary: TableLogger is a handy Python utility for logging tabular data into a console or a file.
Home-page: https://github.com/AleksTk/table-logger
Author: Alexander Tkachenko
Author-email: alex.tk.fb@gmail.com
License: GNU GPL 2.0
Download-URL: https://github.com/AleksTk/table-logger/archive/v0.3.1.tar.gz
Keywords: tabular,structured,data,console,log
Platform: UNKNOWN
Classifier: Development Status :: 5 - Production/Stable
Classifier: Topic :: Software Development :: Libraries
Classifier: Topic :: System :: Logging
Classifier: Programming Language :: Python :: 2.7
Classifier: Programming Language :: Python :: 3
Classifier: Topic :: Software Development :: Libraries :: Python Modules
Classifier: License :: OSI Approved :: GNU General Public License v2 (GPLv2)
